hoi/__init__.py
hoi/core/__init__.py
hoi/core/combinatory.py
hoi/core/entropies.py
hoi/core/mi.py
hoi/core/redundancies.py
hoi/metrics/__init__.py
hoi/metrics/base_hoi.py
hoi/metrics/do_tot.py
hoi/metrics/dtc.py
hoi/metrics/gradient_oinfo.py
hoi/metrics/info_tot.py
hoi/metrics/infotopo.py
hoi/metrics/oinfo.py
hoi/metrics/pairwise_mi.py
hoi/metrics/phiid_atoms.py
hoi/metrics/phiid_red.py
hoi/metrics/pid_atoms.py
hoi/metrics/red_mmi.py
hoi/metrics/rsi.py
hoi/metrics/sinfo.py
hoi/metrics/syn_mmi.py
hoi/metrics/tc.py
hoi/metrics/transfer_entropy.py
hoi/plot/__init__.py
hoi/plot/landscape.py
hoi/simulation/__init__.py
hoi/simulation/simulate_hoi_gauss.py
hoi/utils/__init__.py
hoi/utils/logging.py
hoi/utils/multicores.py
hoi/utils/progressbar.py
hoi/utils/stats.py
hoi-0.0.7.dist-info/licenses/LICENSE
hoi-0.0.7.dist-info/METADATA
hoi-0.0.7.dist-info/WHEEL
hoi-0.0.7.dist-info/top_level.txt
hoi-0.0.7.dist-info/RECORD
