Metadata-Version: 2.4
Name: hoi
Version: 0.0.7
Summary: Higher Order Interactions
Home-page: https://github.com/brainets/hoi
Download-URL: https://github.com/brainets/hoi/archive/v0.0.7.tar.gz
Author: BraiNets
Author-email: e.combrisson@gmail.com
Maintainer: Etienne Combrisson
License: BSD 3-Clause License
Keywords: information-theory statistics higher-order-interactions
Platform: any
Classifier: Development Status :: 3 - Alpha
Classifier: Intended Audience :: Science/Research
Classifier: Intended Audience :: Education
Classifier: Intended Audience :: Developers
Classifier: Topic :: Scientific/Engineering :: Visualization
Classifier: Programming Language :: Python :: 3.8
Classifier: Programming Language :: Python :: 3.9
Classifier: Programming Language :: Python :: 3.10
Classifier: Programming Language :: Python :: 3.11
License-File: LICENSE
Requires-Dist: jax
Requires-Dist: jaxlib
Requires-Dist: numpy>=1.22
Requires-Dist: scipy>=1.9
Requires-Dist: scikit-learn
Requires-Dist: pandas
Requires-Dist: jax-tqdm
Requires-Dist: tqdm
Provides-Extra: test
Requires-Dist: jax; extra == "test"
Requires-Dist: jaxlib; extra == "test"
Requires-Dist: numpy>=1.22; extra == "test"
Requires-Dist: scipy>=1.9; extra == "test"
Requires-Dist: scikit-learn; extra == "test"
Requires-Dist: pandas; extra == "test"
Requires-Dist: jax-tqdm; extra == "test"
Requires-Dist: tqdm; extra == "test"
Requires-Dist: pytest; extra == "test"
Requires-Dist: pytest-cov; extra == "test"
Requires-Dist: codecov; extra == "test"
Requires-Dist: xarray; extra == "test"
Provides-Extra: doc
Requires-Dist: jax; extra == "doc"
Requires-Dist: jaxlib; extra == "doc"
Requires-Dist: numpy>=1.22; extra == "doc"
Requires-Dist: scipy>=1.9; extra == "doc"
Requires-Dist: scikit-learn; extra == "doc"
Requires-Dist: pandas; extra == "doc"
Requires-Dist: jax-tqdm; extra == "doc"
Requires-Dist: tqdm; extra == "doc"
Requires-Dist: sphinx!=4.1.0; extra == "doc"
Requires-Dist: sphinx-gallery; extra == "doc"
Requires-Dist: sphinx_design; extra == "doc"
Requires-Dist: sphinx-book-theme; extra == "doc"
Requires-Dist: sphinxcontrib-bibtex; extra == "doc"
Requires-Dist: sphinx_contributors; extra == "doc"
Requires-Dist: numpydoc; extra == "doc"
Requires-Dist: matplotlib; extra == "doc"
Requires-Dist: xgi; extra == "doc"
Provides-Extra: lint
Requires-Dist: jax; extra == "lint"
Requires-Dist: jaxlib; extra == "lint"
Requires-Dist: numpy>=1.22; extra == "lint"
Requires-Dist: scipy>=1.9; extra == "lint"
Requires-Dist: scikit-learn; extra == "lint"
Requires-Dist: pandas; extra == "lint"
Requires-Dist: jax-tqdm; extra == "lint"
Requires-Dist: tqdm; extra == "lint"
Requires-Dist: flake8; extra == "lint"
Requires-Dist: pep8-naming; extra == "lint"
Requires-Dist: black; extra == "lint"
Provides-Extra: full
Requires-Dist: jax; extra == "full"
Requires-Dist: jaxlib; extra == "full"
Requires-Dist: numpy>=1.22; extra == "full"
Requires-Dist: scipy>=1.9; extra == "full"
Requires-Dist: scikit-learn; extra == "full"
Requires-Dist: pandas; extra == "full"
Requires-Dist: jax-tqdm; extra == "full"
Requires-Dist: tqdm; extra == "full"
Requires-Dist: pytest; extra == "full"
Requires-Dist: pytest-cov; extra == "full"
Requires-Dist: codecov; extra == "full"
Requires-Dist: xarray; extra == "full"
Requires-Dist: sphinx!=4.1.0; extra == "full"
Requires-Dist: sphinx-gallery; extra == "full"
Requires-Dist: sphinx_design; extra == "full"
Requires-Dist: sphinx-book-theme; extra == "full"
Requires-Dist: sphinxcontrib-bibtex; extra == "full"
Requires-Dist: sphinx_contributors; extra == "full"
Requires-Dist: numpydoc; extra == "full"
Requires-Dist: matplotlib; extra == "full"
Requires-Dist: xgi; extra == "full"
Requires-Dist: flake8; extra == "full"
Requires-Dist: pep8-naming; extra == "full"
Requires-Dist: black; extra == "full"
Dynamic: author
Dynamic: author-email
Dynamic: classifier
Dynamic: description
Dynamic: download-url
Dynamic: home-page
Dynamic: keywords
Dynamic: license
Dynamic: license-file
Dynamic: maintainer
Dynamic: platform
Dynamic: provides-extra
Dynamic: requires-dist
Dynamic: summary
